README.rst
setup.cfg
setup.py
src/PyCrack/DIC.py
src/PyCrack/Vectorization.py
src/PyCrack/__init__.py
src/PyCrack.egg-info/PKG-INFO
src/PyCrack.egg-info/SOURCES.txt
src/PyCrack.egg-info/dependency_links.txt
src/PyCrack.egg-info/requires.txt
src/PyCrack.egg-info/top_level.txt