Metadata-Version: 1.1
Name: PyCrack
Version: 0.0.6
Summary: PyCrack is a Python toolbox for analysis and quantification of cracks structural systems using optical methods.
Home-page: https://github.com/eesd-epfl/PyCrack
Author: Ketson R. M. dos Santos
Author-email: ketson.santos@epfl.ch
License: MIT
Platform: OSX
Platform: Windows
Platform: Linux
Classifier: Programming Language :: Python :: 3
Classifier: Intended Audience :: Science/Research
Classifier: Topic :: Scientific/Engineering :: Image Processing
Classifier: License :: OSI Approved :: MIT License
Classifier: Natural Language :: English
